wemoo_agent
